pong/VERSION
pong/__init__.py
pong/align.py
pong/cm.py
pong/dist_metrics.py
pong/distruct.py
pong/main.py
pong/objects.py
pong/parse.py
pong/write.py
pong/static/.DS_Store
pong/static/pong.css
pong/static/pong.js
pong/static/dependencies/bootstrap-tour.min.css
pong/static/dependencies/bootstrap-tour.min.js
pong/static/dependencies/colorbrewer.v1.min.js
pong/static/dependencies/d3-path.v0.2.min.js
pong/static/dependencies/d3-shape.v0.7.min.js
pong/static/dependencies/d3.tip.v0.6.3.js
pong/static/dependencies/d3.v3.min.js
pong/static/dependencies/jquery-2.1.4.min.js
pong/static/dependencies/jquery-ui.min.css
pong/static/dependencies/jquery-ui.min.js
pong/static/dependencies/modernizr-custom.js
pong/static/dependencies/bootstrap-3.3.5-dist/css/bootstrap.min.css
pong/static/dependencies/bootstrap-3.3.5-dist/fonts/glyphicons-halflings-regular.eot
pong/static/dependencies/bootstrap-3.3.5-dist/fonts/glyphicons-halflings-regular.svg
pong/static/dependencies/bootstrap-3.3.5-dist/fonts/glyphicons-halflings-regular.ttf
pong/static/dependencies/bootstrap-3.3.5-dist/fonts/glyphicons-halflings-regular.woff
pong/static/dependencies/bootstrap-3.3.5-dist/fonts/glyphicons-halflings-regular.woff2
pong/static/dependencies/bootstrap-3.3.5-dist/js/bootstrap.min.js
pong/static/dependencies/font-awesome-4.4.0/css/font-awesome.min.css
pong/static/dependencies/font-awesome-4.4.0/fonts/FontAwesome.otf
pong/static/dependencies/font-awesome-4.4.0/fonts/fontawesome-webfont.eot
pong/static/dependencies/font-awesome-4.4.0/fonts/fontawesome-webfont.svg
pong/static/dependencies/font-awesome-4.4.0/fonts/fontawesome-webfont.ttf
pong/static/dependencies/font-awesome-4.4.0/fonts/fontawesome-webfont.woff
pong/static/dependencies/font-awesome-4.4.0/fonts/fontawesome-webfont.woff2
pong/static/favicon/android-icon-144x144.png
pong/static/favicon/android-icon-192x192.png
pong/static/favicon/android-icon-36x36.png
pong/static/favicon/android-icon-48x48.png
pong/static/favicon/android-icon-72x72.png
pong-1.5.dist-info/LICENSE.ColorBrewer.txt
pong-1.5.dist-info/LICENSE.SIL_OFL.txt
pong-1.5.dist-info/LICENSE.bootstrap.txt
pong-1.5.dist-info/LICENSE.bootstraptour.txt
pong-1.5.dist-info/LICENSE.d3-tip.txt
pong-1.5.dist-info/LICENSE.d3js.txt
pong-1.5.dist-info/LICENSE.jQuery.txt
pong-1.5.dist-info/LICENSE.txt
pong-1.5.dist-info/METADATA
pong-1.5.dist-info/WHEEL
pong-1.5.dist-info/entry_points.txt
pong-1.5.dist-info/top_level.txt
pong-1.5.dist-info/RECORD
