Metadata-Version: 2.1
Name: pong
Version: 1.5
Summary: Ultra-fast analysis and interactive visualization of population structure plots from Structure/Admixture data
Home-page: https://github.com/ramachandran-lab/pong
Author: Aaron Behr
Author-email: aaron_behr@alumni.brown.edu
License: UNKNOWN
Project-URL: Issue Tracker, https://github.com/ramachandran-lab/pong/issues
Project-URL: Project Page, https://brown.edu/Research/Ramachandran_Lab/projects/
Project-URL: Original Paper, https://doi.org/10.1093/bioinformatics/btw327
Platform: UNKNOWN
Classifier: Development Status :: 5 - Production/Stable
Classifier: Intended Audience :: Science/Research
Classifier: Topic :: Scientific/Engineering :: Bio-Informatics
Classifier: Topic :: Scientific/Engineering :: Visualization
Classifier: License :: OSI Approved :: GNU General Public License v3 (GPLv3)
Classifier: Natural Language :: English
Classifier: Operating System :: OS Independent
Classifier: Operating System :: MacOS
Classifier: Operating System :: POSIX :: Linux
Classifier: Operating System :: Unix
Classifier: Programming Language :: Python :: 3
Requires-Python: >=3.6
License-File: license/LICENSE.ColorBrewer.txt
License-File: license/LICENSE.bootstrap.txt
License-File: license/LICENSE.d3-tip.txt
License-File: license/LICENSE.jQuery.txt
License-File: license/LICENSE.SIL_OFL.txt
License-File: license/LICENSE.bootstraptour.txt
License-File: license/LICENSE.d3js.txt
License-File: license/LICENSE.txt
